lib3mf/Lib3MF.py
lib3mf/__init__.py
lib3mf/lib3mf.dll
lib3mf-2.4.1.dist-info/LICENSE
lib3mf-2.4.1.dist-info/METADATA
lib3mf-2.4.1.dist-info/WHEEL
lib3mf-2.4.1.dist-info/top_level.txt
lib3mf-2.4.1.dist-info/RECORD
