Metadata-Version: 2.1
Name: lib3mf
Version: 2.4.1
Summary: lib3mf is an implementation of the 3D Manufacturing Format file standard
Classifier: Development Status :: 5 - Production/Stable
Classifier: Intended Audience :: Developers
Classifier: License :: OSI Approved :: BSD License
Classifier: Programming Language :: Python :: 3
Classifier: Operating System :: OS Independent
License-File: LICENSE
